odoo10_addon_mail_sendgrid_mass_mailing-10.0.1.0.2-py3.8-nspkg.pth
odoo/addons/mail_sendgrid_mass_mailing/README.rst
odoo/addons/mail_sendgrid_mass_mailing/__init__.py
odoo/addons/mail_sendgrid_mass_mailing/__manifest__.py
odoo/addons/mail_sendgrid_mass_mailing/i18n/mail_sendgrid_mass_mailing.pot
odoo/addons/mail_sendgrid_mass_mailing/models/__init__.py
odoo/addons/mail_sendgrid_mass_mailing/models/email_tracking.py
odoo/addons/mail_sendgrid_mass_mailing/models/mail_mail.py
odoo/addons/mail_sendgrid_mass_mailing/models/mass_mailing.py
odoo/addons/mail_sendgrid_mass_mailing/static/description/icon.png
odoo/addons/mail_sendgrid_mass_mailing/static/description/icon.svg
odoo/addons/mail_sendgrid_mass_mailing/tests/__init__.py
odoo/addons/mail_sendgrid_mass_mailing/tests/test_mass_mailing.py
odoo/addons/mail_sendgrid_mass_mailing/views/mass_mailing_view.xml
odoo/addons/mail_sendgrid_mass_mailing/wizards/__init__.py
odoo/addons/mail_sendgrid_mass_mailing/wizards/mail_compose_message.py
odoo/addons/mail_sendgrid_mass_mailing/wizards/test_mailing.py
odoo10_addon_mail_sendgrid_mass_mailing-10.0.1.0.2.dist-info/METADATA
odoo10_addon_mail_sendgrid_mass_mailing-10.0.1.0.2.dist-info/WHEEL
odoo10_addon_mail_sendgrid_mass_mailing-10.0.1.0.2.dist-info/namespace_packages.txt
odoo10_addon_mail_sendgrid_mass_mailing-10.0.1.0.2.dist-info/top_level.txt
odoo10_addon_mail_sendgrid_mass_mailing-10.0.1.0.2.dist-info/RECORD
