Metadata-Version: 2.1
Name: odoo10-addon-mail-sendgrid-mass-mailing
Version: 10.0.1.0.2
Summary: Mass Mailing with SendGrid
Home-page: https://github.com/OCA/social
Author: Compassion CH, Odoo Community Association (OCA)
Author-email: support@odoo-community.org
License: AGPL-3
Platform: UNKNOWN
Classifier: Programming Language :: Python
Classifier: Framework :: Odoo
Classifier: Framework :: Odoo :: 10.0
Classifier: License :: OSI Approved :: GNU Affero General Public License v3
Requires-Python: ~=2.7
Requires-Dist: odoo10-addon-mail-sendgrid
Requires-Dist: odoo10-addon-mail-tracking-mass-mailing
Requires-Dist: odoo (<10.1dev,>=10.0)
Requires-Dist: sendgrid
